MANIFEST.in
README
__init__.py
__pkginfo__.py
schema.py
setup.py
site_cubicweb.py
sobjects.py
testlib.py
workflows.py
cubicweb_mediaplayer.egg-info/PKG-INFO
cubicweb_mediaplayer.egg-info/SOURCES.txt
cubicweb_mediaplayer.egg-info/dependency_links.txt
cubicweb_mediaplayer.egg-info/not-zip-safe
cubicweb_mediaplayer.egg-info/requires.txt
cubicweb_mediaplayer.egg-info/top_level.txt
data/cubes.mediaplayer.encoder.css
data/cubes.mediaplayer.encoder.js
data/cubes.mediaplayer.js
data/jplayer/js/circle.player.js
data/jplayer/js/jplayer.playlist.min.js
data/jplayer/js/jquery.grab.js
data/jplayer/js/jquery.jplayer.inspector.js
data/jplayer/js/jquery.jplayer.min.js
data/jplayer/js/jquery.transform2d.js
data/jplayer/js/mod.csstransforms.min.js
data/jplayer/js/popcorn.jplayer.js
data/jplayer/js/popcorn.js
data/jplayer/js/popcorn.player.js
data/jplayer/js/popcorn.subtitle.js
data/jplayer/skin/simple.css
data/jplayer/skin/blue.monday/jplayer.blue.monday.css
data/jplayer/skin/blue.monday/jplayer.blue.monday.jpg
data/jplayer/skin/blue.monday/jplayer.blue.monday.seeking.gif
data/jplayer/skin/blue.monday/jplayer.blue.monday.video.play.png
data/jplayer/skin/circle.skin/bgr.jpg
data/jplayer/skin/circle.skin/buffer.png
data/jplayer/skin/circle.skin/circle.player.css
data/jplayer/skin/circle.skin/controls.jpg
data/jplayer/skin/circle.skin/progress.png
data/jplayer/skin/circle.skin/progress_sprite.jpg
data/jplayer/skin/pink.flag/jplayer.pink.flag.css
data/jplayer/skin/pink.flag/jplayer.pink.flag.jpg
data/jplayer/skin/pink.flag/jplayer.pink.flag.seeking.gif
data/jplayer/skin/pink.flag/jplayer.pink.flag.video.play.png
entities/__init__.py
entities/adapters.py
hooks/__init__.py
hooks/bfss.py
i18n/en.po
i18n/es.po
i18n/fr.po
migration/0.2.0_Any.py
migration/postcreate.py
test/pytestconf.py
test/unittest_sound_files.py
test/unittest_tasks.py
test/unittest_video_files.py
utils/__init__.py
utils/media.py
views/__init__.py
views/encoder.py
views/loader.py
views/media.py
views/players.py
views/urlrewrite.py
views/htmltemplates/jplayer-audio.html
views/htmltemplates/multi-jplayer-audio.html
views/htmltemplates/multi-jplayer-video.html