Metadata-Version: 1.1
Name: cubicweb-mediaplayer
Version: 0.2.2
Summary: provide a schema and API for sound and media files with a html5 player
Home-page: http://www.cubicweb.org/project/cubicweb-mediaplayer
Author: LOGILAB S.A. (Paris, FRANCE)
Author-email: contact@logilab.fr
License: LGPL
Platform: UNKNOWN
Classifier: Environment :: Web Environment
Classifier: Framework :: CubicWeb
Classifier: Programming Language :: Python
Classifier: Programming Language :: JavaScript
